LICENSE
MANIFEST.in
README.md
pyproject.toml
setup.cfg
setup.py
src/pymser/__init__.py
src/pymser/pymser.py
src/pymser.egg-info/PKG-INFO
src/pymser.egg-info/SOURCES.txt
src/pymser.egg-info/dependency_links.txt
src/pymser.egg-info/requires.txt
src/pymser.egg-info/top_level.txt