Metadata-Version: 2.1
Name: pymser
Version: 1.0.10
Summary: Library to apply the Marginal Standard Error Rule for transient regime detection and truncation on Grand Canonical Monte Carlo adsorption simulations
Home-page: https://github.com/IBM/pymser
Author: Felipe Lopes de Oliveira
Author-email: felipe.lopes.oliveira@ibm.com
License: BSD 3-Clause License
Classifier: Programming Language :: Python :: 3
Classifier: Operating System :: OS Independent
Classifier: License :: OSI Approved :: BSD License
Requires-Python: >=3.9
License-File: LICENSE
